MultiPartForm.py
Ziggeo.py
ZiggeoAnalytics.py
ZiggeoApplication.py
ZiggeoAudioStreams.py
ZiggeoAudios.py
ZiggeoAuth.py
ZiggeoAuthtokens.py
ZiggeoConfig.py
ZiggeoConnect.py
ZiggeoEffectProfileProcess.py
ZiggeoEffectProfiles.py
ZiggeoMetaProfileProcess.py
ZiggeoMetaProfiles.py
ZiggeoStreams.py
ZiggeoVideos.py
ZiggeoWebhooks.py
__init__.py
ziggeo-2.30.dist-info/LICENSE.md
ziggeo-2.30.dist-info/METADATA
ziggeo-2.30.dist-info/WHEEL
ziggeo-2.30.dist-info/top_level.txt
ziggeo-2.30.dist-info/RECORD
