Metadata-Version: 2.1
Name: ziggeo
Version: 2.30
Summary: Ziggeo SDK for python
Home-page: http://github.com/Ziggeo/ZiggeoPythonSdk
Author: Ziggeo
Author-email: support@ziggeo.com
License: Apache 2.0
Keywords: Ziggeo video-upload
Platform: UNKNOWN
Classifier: Intended Audience :: Developers
Classifier: License :: OSI Approved :: Apache Software License
Classifier: Programming Language :: Python :: 3
License-File: LICENSE.md
Requires-Dist: pycryptodome (>=3.7.0)
